FnF/Filenames.py
FnF/Humansort.py
FnF/ListMethods.py
FnF/PathStr.py
FnF/SplitSep.py
FnF/__init__.py
FnF-2.0.0.dist-info/METADATA
FnF-2.0.0.dist-info/WHEEL
FnF-2.0.0.dist-info/top_level.txt
FnF-2.0.0.dist-info/RECORD
