Metadata-Version: 2.1
Name: FnF
Version: 2.0.0
Summary: Library to work with Files 'n' Folders
Home-page: UNKNOWN
Author: Alan Bacon
Author-email: alan@bacontowers.co.uk
License: UNKNOWN
Platform: UNKNOWN
Requires-Dist: pyAbstracts (>=1)
Requires-Dist: StringQuartet (>=1)
